thinkgisdump/__init__.py
thinkgisdump/cli.py
thinkgisdump/geom.py
thinkgisdump-0.2.1.dist-info/entry_points.txt
thinkgisdump-0.2.1.dist-info/LICENSE
thinkgisdump-0.2.1.dist-info/WHEEL
thinkgisdump-0.2.1.dist-info/METADATA
thinkgisdump-0.2.1.dist-info/RECORD
