Metadata-Version: 2.1
Name: thinkgisdump
Version: 0.2.1
Summary: Command line tool for scraping GeoJSON from ThinkGIS sites
Home-page: https://github.com/pjsier/thinkgisdump
License: MIT
Author: Pat Sier
Author-email: pjsier@gmail.com
Requires-Python: >=3.6.1,<4.0
Classifier: License :: OSI Approved :: MIT License
Classifier: Programming Language :: Python :: 3
Classifier: Programming Language :: Python :: 3.10
Classifier: Programming Language :: Python :: 3.7
Classifier: Programming Language :: Python :: 3.8
Classifier: Programming Language :: Python :: 3.9
Requires-Dist: geojson-rewind (>=1.0.2,<2.0.0)
Requires-Dist: lxml (>=4.7.1,<5.0.0)
Requires-Dist: requests (>=2.27.1,<3.0.0)
Project-URL: Repository, https://github.com/pjsier/thinkgisdump
